{
  "content_hash": "95ee0317a59bde4c6bd7c7e7219e1b33",
  "timestamp": "2025-09-24T17:05:29.289341+07:00",
  "result": {
    "language": "YAML",
    "purpose": "Configuration file for GoReleaser to manage project releases.",
    "key_types": [
      "project_name",
      "builds",
      "changelog",
      "groups"
    ],
    "functions": [
      "skip",
      "disable",
      "use",
      "sort",
      "groups"
    ],
    "imports": [],
    "side_effects": [
      "May affect the release process based on configuration settings."
    ],
    "risks": [
      "Potential for incorrect release notes if changelog generation is misconfigured."
    ],
    "complexity": "medium"
  }
}