{
  "content_hash": "913cd3fbc0f4605b00ea6a69510151e9",
  "timestamp": "2025-09-26T08:29:10.203633+07:00",
  "result": {
    "language": "SQL",
    "purpose": "[REDACTED]",
    "key_types": [
      "jsonb"
    ],
    "functions": [
      "ALTER TABLE"
    ],
    "imports": [],
    "side_effects": [
      "Modifies the database schema by adding and dropping a column."
    ],
    "risks": [
      "Potential data loss if the column is dropped without proper backups."
    ],
    "complexity": "low"
  }
}