{
  "content_hash": "3860619df89d8db5239d89c97e26c9f1",
  "timestamp": "2025-09-24T15:28:47.946127+07:00",
  "result": {
    "language": "JavaScript",
    "purpose": "Defines a React component that uses memoization and maps over an array.",
    "key_types": [
      "Function",
      "Array"
    ],
    "functions": [
      "Component",
      "_temp"
    ],
    "imports": [
      "react/compiler-runtime"
    ],
    "side_effects": [
      "Modifies the cache sentinel for memoization"
    ],
    "complexity": "medium"
  }
}