{
  "content_hash": "f28b718b3c73d1ea6a482ce1b408e4b9",
  "timestamp": "2025-09-24T16:40:55.749492+07:00",
  "result": {
    "language": "Go",
    "purpose": "This file appears to be a test case for fuzz testing in Go, specifically for parsing JSON data.",
    "key_types": [
      "byte",
      "string"
    ],
    "functions": [
      "testFuzzParse"
    ],
    "imports": [
      "testing",
      "encoding/json"
    ],
    "side_effects": [
      "None"
    ],
    "risks": [
      "None"
    ],
    "complexity": "low"
  }
}