{
  "content_hash": "97ee8a45855e79986f7c6a21f3492fe5",
  "timestamp": "2025-09-25T17:44:51.072019+07:00",
  "result": {
    "path": "internal/bytesconv",
    "purpose": "Provides functions to convert between strings and byte slices without memory allocation.",
    "languages": {
      "Go": 2
    },
    "key_modules": [
      "bytesconv.go",
      "bytesconv_test.go"
    ],
    "dependencies": [
      "unsafe",
      "bytes",
      "crypto/rand",
      "math/rand",
      "strings",
      "testing",
      "time"
    ],
    "architecture": "The folder follows a modular architecture pattern, encapsulating functionality related to byte and string conversions in a dedicated module with accompanying tests.",
    "file_summaries": {
      "internal/bytesconv/bytesconv.go": {
        "language": "Go",
        "purpose": "Provides functions to convert between strings and byte slices without memory allocation.",
        "key_types": [
          "string",
          "[]byte"
        ],
        "functions": [
          "StringToBytes",
          "BytesToString"
        ],
        "imports": [
          "unsafe"
        ],
        "risks": [
          "unsafe memory operations may lead to vulnerabilities if not handled properly"
        ],
        "complexity": "medium"
      },
      "internal/bytesconv/bytesconv_test.go": {
        "language": "Go",
        "purpose": "This file contains tests and benchmarks for converting between bytes and strings.",
        "key_types": [
          "string",
          "[]byte",
          "testing.T"
        ],
        "functions": [
          "rawBytesToStr",
          "rawStrToBytes",
          "RandStringBytesMaskImprSrcSB",
          "TestBytesToString",
          "TestStringToBytes",
          "BenchmarkBytesConvBytesToStrRaw",
          "BenchmarkBytesConvBytesToStr",
          "BenchmarkBytesConvStrToBytesRaw",
          "BenchmarkBytesConvStrToBytes"
        ],
        "imports": [
          "bytes",
          "crypto/rand",
          "math/rand",
          "strings",
          "testing",
          "time"
        ],
        "side_effects": [
          "Generates random bytes using crypto/rand",
          "Uses time for random seed generation"
        ],
        "risks": [
          "Potential for non-deterministic behavior in tests due to randomness"
        ],
        "complexity": "medium"
      }
    }
  }
}