{
  "content_hash": "470d30499d13a5a936f8c1af19e09ea1",
  "timestamp": "2025-09-25T15:33:48.23313+07:00",
  "result": {
    "language": "Ruby",
    "purpose": "Defines callbacks for Action Cable connections to handle commands sent to clients.",
    "key_types": [
      "ActionCable::Connection::Base",
      "ActiveSupport::Concern",
      "ActiveSupport::Callbacks"
    ],
    "functions": [
      "before_command",
      "after_command",
      "around_command"
    ],
    "imports": [
      "active_support/callbacks"
    ],
    "complexity": "medium"
  }
}