{
  "content_hash": "98e29da9a64763e53fb763c0a4b900cc",
  "timestamp": "2025-09-24T15:44:49.600957+07:00",
  "result": {
    "language": "Go",
    "purpose": "This file contains functions for decoding HCL (HashiCorp Configuration Language) bodies into structured data types.",
    "key_types": [
      "hcl.Body",
      "blockLabel",
      "hcl.EvalContext",
      "Spec",
      "cty.Value",
      "hcl.Diagnostics"
    ],
    "functions": [
      "decode",
      "impliedType",
      "sourceRange"
    ],
    "imports": [
      "github.com/hashicorp/hcl/v2",
      "github.com/zclconf/go-cty/cty"
    ],
    "complexity": "medium"
  }
}