{
  "content_hash": "a05e9964afccf2ce49ce7ee53f28393a",
  "timestamp": "2025-09-25T15:50:42.797335+07:00",
  "result": {
    "language": "JSON",
    "purpose": "Configuration file for a Node.js development container",
    "key_types": [
      "object",
      "string",
      "array"
    ],
    "functions": [
      "postCreateCommand"
    ],
    "imports": [
      "mcr.microsoft.com/devcontainers/javascript-node:0-18",
      "ghcr.io/devcontainers/features/git:1"
    ],
    "side_effects": [
      "Installs dependencies using yarn",
      "Configures VS Code extensions"
    ],
    "risks": [
      "Potential exposure of sensitive data if remoteUser is set to root"
    ],
    "complexity": "low"
  }
}