{
  "content_hash": "b52822f4598a446416bf2b0b12a5ac68",
  "timestamp": "2025-09-26T13:22:50.575119+07:00",
  "result": {
    "language": "Go",
    "purpose": "This file defines a repository for managing device data, including CRUD operations and pagination.",
    "key_types": [
      "DeviceRepo",
      "repo",
      "device",
      "models.DeviceFilter",
      "models.OrderBy",
      "models.Device",
      "models.Paging"
    ],
    "functions": [
      "GetDevice",
      "GetDeviceList",
      "CreateDevice",
      "DeleteDevice",
      "UpdateDevice",
      "SaveDevice",
      "BatchSaveDevices",
      "UpdateDevices",
      "SaveDevices",
      "NewDeviceRepo",
      "paginate"
    ],
    "imports": [
      "context",
      "errors",
      "fmt",
      "github.com/samber/lo",
      "gorm.io/gorm",
      "gorm.io/gorm/clause",
      "github.com/axieinfinity/ronin-wallet-services/internal/domains/devicemanager/models",
      "github.com/axieinfinity/ronin-wallet-services/internal/enums"
    ],
    "side_effects": [
      "Database transactions for CRUD operations"
    ],
    "risks": [
      "Potential SQL injection if user input is not properly sanitized in queries"
    ],
    "complexity": "medium"
  }
}