{
  "content_hash": "7527272af520c4c414c2d9e60ae59945",
  "timestamp": "2025-09-26T13:10:26.457241+07:00",
  "result": {
    "language": "Go",
    "purpose": "This file defines a device management service that handles device registration, updates, retrieval, and synchronization of device addresses.",
    "key_types": [
      "DeviceService",
      "deviceService",
      "models.Device",
      "models.DeviceFilter",
      "types.WAddress"
    ],
    "functions": [
      "NewDeviceService",
      "RegisterDevice",
      "UpdateDevices",
      "GetDevices",
      "SyncDeviceAddresses",
      "getExistingDeviceMap"
    ],
    "imports": [
      "context",
      "net/http",
      "github.com/samber/lo",
      "go.uber.org/zap",
      "github.com/axieinfinity/ronin-wallet-services/internal/domains/devicemanager/models",
      "github.com/axieinfinity/ronin-wallet-services/internal/domains/devicemanager/repos",
      "github.com/axieinfinity/ronin-wallet-services/internal/enums",
      "github.com/axieinfinity/ronin-wallet-services/pkg/errors",
      "github.com/axieinfinity/ronin-wallet-services/pkg/helper",
      "github.com/axieinfinity/ronin-wallet-services/pkg/types"
    ],
    "side_effects": [
      "Modifies device records in the repository",
      "Logs information about device operations"
    ],
    "risks": [
      "Potential exposure of sensitive information if error messages are not handled properly",
      "Inadequate validation of device data could lead to inconsistent state"
    ],
    "complexity": "medium"
  }
}