{
  "content_hash": "6f152ba9dc1e85a14688e85bd3ba0d60",
  "timestamp": "2025-09-26T13:22:51.347723+07:00",
  "result": {
    "language": "Go",
    "purpose": "Handles routing for a decentralized exchange (DEX) service, including route finding and token retrieval.",
    "key_types": [
      "DexRouterHandler",
      "services.DexRouterService",
      "models.RouteRequest",
      "models.BuildRouteRequest"
    ],
    "functions": [
      "NewDexRouterHandler",
      "Setup",
      "getDexRoutes",
      "buildRoute",
      "getTokens"
    ],
    "imports": [
      "github.com/labstack/echo/v4",
      "github.com/axieinfinity/ronin-wallet-services/internal/domains/dex/handlers/dtos/responses",
      "github.com/axieinfinity/ronin-wallet-services/internal/domains/dex/models",
      "github.com/axieinfinity/ronin-wallet-services/internal/domains/dex/services",
      "github.com/axieinfinity/ronin-wallet-services/internal/routers",
      "github.com/axieinfinity/ronin-wallet-services/pkg/http"
    ],
    "side_effects": [
      "Modifies request context based on region header",
      "Interacts with external services to fetch routes and tokens"
    ],
    "risks": [
      "Potential exposure of sensitive data through error handling",
      "Dependency on external services may lead to failures"
    ],
    "complexity": "medium"
  }
}