{
  "content_hash": "838436c1f8a7abae4024b26d46d570aa",
  "timestamp": "2025-09-24T15:26:03.901585+07:00",
  "result": {
    "language": "TypeScript",
    "purpose": "Defines global objects and their types for a JavaScript environment, aiding in type inference and effect analysis.",
    "key_types": [
      "ShapeRegistry",
      "BuiltInType",
      "ObjectType",
      "PolyType"
    ],
    "functions": [
      "addFunction",
      "addObject",
      "assertExhaustive",
      "isHookName"
    ],
    "imports": [
      "./HIR",
      "./ObjectShape",
      "./Types",
      "./TypeSchema",
      "../Utils/utils"
    ],
    "side_effects": [
      "Modifies global object definitions",
      "Impure functions that may affect state"
    ],
    "complexity": "medium"
  }
}