{
  "content_hash": "296f6f5e318a014ca4c83eb134924fd1",
  "timestamp": "2025-09-24T15:42:39.753403+07:00",
  "result": {
    "language": "Go",
    "purpose": "This file defines a middleware for the Fiber web framework that sets various security-related HTTP headers.",
    "key_types": [
      "Config",
      "fiber.Handler",
      "fiber.Ctx"
    ],
    "functions": [
      "New",
      "configDefault"
    ],
    "imports": [
      "fmt",
      "github.com/gofiber/fiber/v3"
    ],
    "side_effects": [
      "Modifies HTTP response headers based on configuration"
    ],
    "risks": [
      "Improper configuration may lead to security vulnerabilities"
    ],
    "complexity": "medium"
  }
}