{
  "content_hash": "f2ddc06da07e10b3bfa0f6d2d65176d0",
  "timestamp": "2025-09-24T15:41:29.584849+07:00",
  "result": {
    "language": "Go",
    "purpose": "This file documents the Limiter middleware for the Fiber web framework, detailing its configuration and usage for rate limiting requests.",
    "key_types": [
      "Config",
      "fiber.Handler",
      "fiber.Ctx",
      "fiber.Storage",
      "LimiterHandler"
    ],
    "functions": [
      "New",
      "Next",
      "MaxFunc",
      "KeyGenerator",
      "LimitReached"
    ],
    "imports": [
      "github.com/gofiber/fiber/v3",
      "github.com/gofiber/fiber/v3/middleware/limiter"
    ],
    "side_effects": [
      "Redacts request keys in error paths to prevent sensitive information from being logged.",
      "Can modify request handling based on rate limiting rules."
    ],
    "risks": [
      "Potential for denial of service if limits are set too low.",
      "Improper configuration may lead to unintentional exposure of sensitive data."
    ],
    "complexity": "medium"
  }
}