{
  "content_hash": "05e623964b66761a4bed3f19a04e4cca",
  "timestamp": "2025-09-18T15:30:14.792872+07:00",
  "result": {
    "language": "Go",
    "purpose": "Auth service handles authentication and authorization",
    "key_types": [
      "echo.Context"
    ],
    "functions": [
      "main",
      "login",
      "validateToken"
    ],
    "imports": [
      "github.com/labstack/echo/v4",
      "net/http"
    ],
    "side_effects": [
      "Starts an HTTP server on port 3002"
    ],
    "risks": [
      "Potential exposure of sensitive token information"
    ],
    "complexity": "medium"
  }
}