{
  "content_hash": "57d4acc2d62659497f27ac7127c75e8b",
  "timestamp": "2025-09-26T12:38:43.214252+07:00",
  "result": {
    "language": "Go",
    "purpose": "This file provides a function to decode a map into a struct and validate it using the validator package.",
    "key_types": [
      "T",
      "map[string]any",
      "error"
    ],
    "functions": [
      "DecodeStructAndValidate"
    ],
    "imports": [
      "github.com/go-playground/validator/v10",
      "github.com/mitchellh/mapstructure"
    ],
    "complexity": "medium"
  }
}