{
  "content_hash": "905ff69295b757dd632cee40c9748a25",
  "timestamp": "2025-09-26T13:27:10.989266+07:00",
  "result": {
    "language": "Go",
    "purpose": "This file provides utility functions for decoding and binding struct fields to environment variables using mapstructure.",
    "key_types": [
      "mapstructure.DecodeHookFunc",
      "reflect.Type",
      "viper.Viper",
      "bytesize.ByteSize",
      "types.WAddress"
    ],
    "functions": [
      "StringToByteSizeHookFunc",
      "BindStructPathsToEnvs",
      "extractMapstructurePaths",
      "getMapstructurePath",
      "getAllEnvNamesWithPrefix",
      "ParseSliceOfStructHookFunc",
      "StringToTimeLocationHookFunc",
      "StringToWrapAddressHookFunc"
    ],
    "imports": [
      "fmt",
      "os",
      "reflect",
      "regexp",
      "strings",
      "time",
      "github.com/axieinfinity/ronin-wallet-services/pkg/types",
      "github.com/fatih/structtag",
      "github.com/inhies/go-bytesize",
      "github.com/mitchellh/mapstructure",
      "github.com/spf13/viper",
      "github.com/stoewer/go-strcase"
    ],
    "side_effects": [
      "Modifies the state of the viper instance by binding environment variables."
    ],
    "complexity": "medium"
  }
}