{
  "content_hash": "d9616fcfdafa2e2160b47586dd0e38e5",
  "timestamp": "2025-09-26T13:23:48.509269+07:00",
  "result": {
    "language": "Go",
    "purpose": "Defines a multi-chain provider interface and related types for handling portfolio and transaction data.",
    "key_types": [
      "PaginatedResponse",
      "MultiChainProvider",
      "activitiesListingResp"
    ],
    "functions": [
      "IsAddressSupported",
      "Name",
      "IsMethodSupported",
      "IsAddressSupported",
      "GetPortfolioBalance",
      "ListPortfolioNFTItems",
      "GetTokenFiatInfo",
      "GetPortfolioNftCollections",
      "GetPortfolioActivities",
      "GetCollectionDetail",
      "GetFungibleTxs",
      "GetNftTransfers",
      "ExecuteRpc"
    ],
    "imports": [
      "context",
      "github.com/axieinfinity/ronin-wallet-services/internal/domains/proxy/handlers/dtos/requests",
      "github.com/axieinfinity/ronin-wallet-services/internal/domains/proxy/models",
      "github.com/axieinfinity/ronin-wallet-services/internal/routers/dtos/enums/proxy",
      "github.com/axieinfinity/ronin-wallet-services/pkg/types",
      "github.com/ethereum/go-ethereum/common"
    ],
    "complexity": "medium"
  }
}