{
  "content_hash": "6ee47f14e6cd00cd418e57b724bfb0af",
  "timestamp": "2025-09-26T13:25:47.404492+07:00",
  "result": {
    "language": "Go",
    "purpose": "Defines a request structure for date range queries and provides methods to handle date range logic.",
    "key_types": [
      "RangeDateReq"
    ],
    "functions": [
      "RangeDate",
      "rangeDefault",
      "MapFieldToColumn"
    ],
    "imports": [
      "github.com/axieinfinity/ronin-wallet-services/internal/routers/dtos/enums/discovery"
    ],
    "complexity": "medium"
  }
}