{
  "content_hash": "6410cbd9b3d1d46085cee397cd4282b5",
  "timestamp": "2025-09-24T15:44:27.85296+07:00",
  "result": {
    "path": ".github/scripts",
    "purpose": "Automates the synchronization of documentation based on GitHub events (push and release).",
    "languages": {
      "bash": 1
    },
    "key_modules": [
      "sync_docs.sh"
    ],
    "dependencies": [],
    "architecture": "The folder contains scripts that automate tasks related to GitHub events, following a procedural architecture pattern.",
    "file_summaries": {
      ".github/scripts/sync_docs.sh": {
        "language": "bash",
        "purpose": "Automates the synchronization of documentation based on GitHub events (push and release).",
        "key_types": [],
        "functions": [],
        "imports": [],
        "side_effects": [
          "Modifies git configuration for user email and name.",
          "Clones a repository.",
          "Copies documentation files.",
          "Commits changes to the repository.",
          "Pushes changes to the remote repository."
        ],
        "risks": [
          "Potential exposure of sensitive information in the repository URL.",
          "Risk of overwriting existing documentation if not handled properly."
        ],
        "complexity": "medium"
      }
    }
  }
}