{
  "content_hash": "24818d96412311651579465cf3d88de2",
  "timestamp": "2025-09-26T12:24:42.968123+07:00",
  "result": {
    "language": "Go",
    "purpose": "This file contains functions to manage user rewards in a quest system, including finding eligible rewards, distributing rewards, and updating user actions.",
    "key_types": [
      "userReward",
      "UserQuestReward",
      "QuestListingItem",
      "QuestRewardExtra",
      "UserQuestItem",
      "UserAction",
      "RewardPoolExtra"
    ],
    "functions": [
      "findEligibleUserRewards",
      "queueDistributeOrderV4",
      "getOnChainAmounts",
      "getOffChainAmounts",
      "createUserRewards",
      "prepareUpdateFns",
      "assureQuestInProgress",
      "assureActionVerifiable",
      "assureActionUpdated"
    ],
    "imports": [
      "context",
      "errors",
      "strings",
      "time",
      "github.com/ethereum/go-ethereum/common",
      "github.com/samber/lo",
      "github.com/shopspring/decimal",
      "github.com/axieinfinity/ronin-wallet-services/internal/enums/quest_center",
      "github.com/axieinfinity/ronin-wallet-services/internal/repositories/models",
      "github.com/axieinfinity/ronin-wallet-services/internal/routers/dtos/responses",
      "github.com/axieinfinity/ronin-wallet-services/internal/services/reward-distribution",
      "github.com/axieinfinity/ronin-wallet-services/pkg/helper"
    ],
    "side_effects": [
      "Interacts with external services to fetch on-chain reward data.",
      "Enqueues tasks for reward distribution."
    ],
    "risks": [
      "Potential for errors in fetching or processing rewards.",
      "Improper handling of user input could lead to unexpected behavior."
    ],
    "complexity": "medium"
  }
}